babel_godot.py
Babel_Godot-1.2.dist-info/LICENSE
Babel_Godot-1.2.dist-info/METADATA
Babel_Godot-1.2.dist-info/WHEEL
Babel_Godot-1.2.dist-info/entry_points.txt
Babel_Godot-1.2.dist-info/top_level.txt
Babel_Godot-1.2.dist-info/RECORD
