Metadata-Version: 2.1
Name: Babel-Godot
Version: 1.2
Summary: Plugin for Babel to support Godot scene files (.tscn)
Home-page: https://github.com/remram44/pybabel-godot
Author: Remi Rampin
Author-email: remirampin@gmail.com
License: BSD
Platform: UNKNOWN
Classifier: Development Status :: 5 - Production/Stable
Classifier: Intended Audience :: Developers
Classifier: License :: OSI Approved :: BSD License
Classifier: Operating System :: OS Independent
Classifier: Programming Language :: Python
Classifier: Programming Language :: Python :: 2.7
Classifier: Programming Language :: Python :: 3
Classifier: Topic :: Software Development :: Libraries :: Python Modules
Requires-Python: >=2.7, !=3.0.*, !=3.1.*, !=3.2.*, !=3.3.*
